apiweaver/__init__.py
apiweaver/cli.py
apiweaver/models.py
apiweaver/server.py
mseep_apiweaver-0.2.6.dist-info/METADATA
mseep_apiweaver-0.2.6.dist-info/WHEEL
mseep_apiweaver-0.2.6.dist-info/entry_points.txt
mseep_apiweaver-0.2.6.dist-info/licenses/LICENSE
mseep_apiweaver-0.2.6.dist-info/RECORD
